asyncio_simple_http_server/__init__.py
asyncio_simple_http_server/http_util.py
asyncio_simple_http_server/humans.py
asyncio_simple_http_server/metrics.py
asyncio_simple_http_server/server.py
asyncio_simple_http_server-0.0.8.dist-info/METADATA
asyncio_simple_http_server-0.0.8.dist-info/WHEEL
asyncio_simple_http_server-0.0.8.dist-info/licenses/LICENSE
asyncio_simple_http_server-0.0.8.dist-info/RECORD
