Metadata-Version: 2.3
Name: asyncio_simple_http_server
Version: 0.0.8
Summary: A Simple Http API Server using asyncio
Project-URL: Homepage, https://github.com/matteobertozzi/asyncio-simple-http-server
Project-URL: Bug Tracker, https://github.com/matteobertozzi/asyncio-simple-http-server/issues
Author-email: Matteo Bertozzi <mbertozzi@apache.org>
License-File: LICENSE
Classifier: License :: OSI Approved :: Apache Software License
Classifier: Operating System :: OS Independent
Classifier: Programming Language :: Python :: 3
Requires-Python: >=3.8
